jisa-stubs/__init__.pyi
jisa-stubs/addresses/__init__.pyi
jisa-stubs/control/__init__.pyi
jisa-stubs/devices/__init__.pyi
jisa-stubs/devices/amp/__init__.pyi
jisa-stubs/devices/camera/__init__.pyi
jisa-stubs/devices/funcgen/__init__.pyi
jisa-stubs/devices/interfaces/__init__.pyi
jisa-stubs/devices/level/__init__.pyi
jisa-stubs/devices/power/__init__.pyi
jisa-stubs/devices/probestation/__init__.pyi
jisa-stubs/devices/relay/__init__.pyi
jisa-stubs/devices/smu/__init__.pyi
jisa-stubs/devices/spectrometer/__init__.pyi
jisa-stubs/devices/temperature/__init__.pyi
jisa-stubs/devices/vmeter/__init__.pyi
jisa-stubs/enums/__init__.pyi
jisa-stubs/experiment/__init__.pyi
jisa-stubs/experiment/queue/__init__.pyi
jisa-stubs/gui/__init__.pyi
jisa-stubs/gui/fields/__init__.pyi
jisa-stubs/gui/fxml/__init__.pyi
jisa-stubs/gui/plotting/__init__.pyi
jisa-stubs/gui/queue/__init__.pyi
jisa-stubs/gui/svg/__init__.pyi
jisa-stubs/logging/__init__.pyi
jisa-stubs/maths/__init__.pyi
jisa-stubs/maths/fits/__init__.pyi
jisa-stubs/maths/functions/__init__.pyi
jisa-stubs/maths/interpolation/__init__.pyi
jisa-stubs/maths/matrices/__init__.pyi
jisa-stubs/maths/matrices/exceptions/__init__.pyi
jisa-stubs/maths/nd/__init__.pyi
jisa-stubs/results/__init__.pyi
jisa-stubs/visa/__init__.pyi
jisa-stubs/visa/connections/__init__.pyi
jisa-stubs/visa/drivers/__init__.pyi
jisa-stubs/visa/exceptions/__init__.pyi
jisa_stubs-1.2.dist-info/METADATA
jisa_stubs-1.2.dist-info/WHEEL
jisa_stubs-1.2.dist-info/top_level.txt
jisa_stubs-1.2.dist-info/RECORD
