Metadata-Version: 2.1
Name: jisa-stubs
Version: 1.2
Summary: JISA Python wrapper stubs
Home-page: https://github.com/OE-FET/JISA.git
Author: William Wood
Author-email: waw31@cam.ac.uk
License: unlicense
